{


	"lalicemail":{
		"prefix":"lalicemail",
		"body":[
			"\\lalicemail"
		],
		"luasnip": {"priority": 3000} 
	},


	"email{}":{
		"prefix":"email",
		"body":[
			"\\email{${1:email%URL}}"
		],
		"luasnip": {"priority": 3000} 
	},


	"dataapresentacao{}{}{}":{
		"prefix":"dataapresentacao",
		"body":[
			"\\dataapresentacao{${1:day}}{${2:month}}{${3:year}}"
		],
		"luasnip": {"priority": 3000} 
	},


	"agendaautomatica":{
		"prefix":"agendaautomatica",
		"body":[
			"\\agendaautomatica"
		],
		"luasnip": {"priority": 3000} 
	},


	"agendaautomatica[]":{
		"prefix":"agendaautomatica",
		"body":[
			"\\agendaautomatica[${1:number}]"
		],
		"luasnip": {"priority": 1000} 
	},


	"segundacoluna":{
		"prefix":"segundacoluna",
		"body":[
			"\\segundacoluna"
		],
		"luasnip": {"priority": 3000} 
	},


	"progressbar":{
		"prefix":"progressbar",
		"body":[
			"\\progressbar"
		],
		"luasnip": {"priority": 3000} 
	}
}
