{


	"punctstyle{}":{
		"prefix":"punctstyle",
		"body":[
			"\\punctstyle{${1:style%keyvals}}"
		],
		"luasnip": {"priority": 3000} 
	},


	"CJKpunctallowbreakbetweenpuncts":{
		"prefix":"CJKpunctallowbreakbetweenpuncts",
		"body":[
			"\\CJKpunctallowbreakbetweenpuncts"
		],
		"luasnip": {"priority": 3000} 
	},


	"CJKpunctnobreakbetweenpuncts":{
		"prefix":"CJKpunctnobreakbetweenpuncts",
		"body":[
			"\\CJKpunctnobreakbetweenpuncts"
		],
		"luasnip": {"priority": 3000} 
	},


	"CJKpunctsetkern{}{}{}":{
		"prefix":"CJKpunctsetkern",
		"body":[
			"\\CJKpunctsetkern{${1:标点1}}{${2:标点2}}{${3:间距}}"
		],
		"luasnip": {"priority": 3000} 
	},


	"CJKpunctmapfamily{}{}{}{}{}":{
		"prefix":"CJKpunctmapfamily",
		"body":[
			"\\CJKpunctmapfamily{${1:encoding}}{${2:family}}{${3:series}}{${4:shape}}{${5:punct family}}"
		],
		"luasnip": {"priority": 3000} 
	}
}
