{


	"newboxarray{}":{
		"prefix":"newboxarray",
		"body":[
			"\\newboxarray{${1:name}}"
		],
		"luasnip": {"priority": 3000} 
	},


	"boxarrayreset":{
		"prefix":"boxarrayreset",
		"body":[
			"\\boxarrayreset"
		],
		"luasnip": {"priority": 3000} 
	},


	"boxarrayreset[]":{
		"prefix":"boxarrayreset",
		"body":[
			"\\boxarrayreset[${1:name}]"
		],
		"luasnip": {"priority": 1000} 
	},


	"boxarrayclear":{
		"prefix":"boxarrayclear",
		"body":[
			"\\boxarrayclear"
		],
		"luasnip": {"priority": 3000} 
	},


	"boxarrayclear[]":{
		"prefix":"boxarrayclear",
		"body":[
			"\\boxarrayclear[${1:name}]"
		],
		"luasnip": {"priority": 1000} 
	},


	"boxarraygetsize{}":{
		"prefix":"boxarraygetsize",
		"body":[
			"\\boxarraygetsize{${1:macro%cmd}}"
		],
		"luasnip": {"priority": 3000} 
	},


	"boxarraygetsize[]{}":{
		"prefix":"boxarraygetsize",
		"body":[
			"\\boxarraygetsize[${2:name}]{${1:macro%cmd}}"
		],
		"luasnip": {"priority": 1000} 
	},


	"useboxarray{}":{
		"prefix":"useboxarray",
		"body":[
			"\\useboxarray{${1:index}}"
		],
		"luasnip": {"priority": 3000} 
	},


	"useboxarray[]{}":{
		"prefix":"useboxarray",
		"body":[
			"\\useboxarray[${2:name}]{${1:index}}"
		],
		"luasnip": {"priority": 1000} 
	},


	"usetcboxarray{}{}":{
		"prefix":"usetcboxarray",
		"body":[
			"\\usetcboxarray{${1:index}}{${2:options%keyvals}}"
		],
		"luasnip": {"priority": 3000} 
	},


	"usetcboxarray[]{}{}":{
		"prefix":"usetcboxarray",
		"body":[
			"\\usetcboxarray[${3:name}]{${1:index}}{${2:options%keyvals}}"
		],
		"luasnip": {"priority": 1000} 
	},


	"consumeboxarray{}":{
		"prefix":"consumeboxarray",
		"body":[
			"\\consumeboxarray{${1:index}}"
		],
		"luasnip": {"priority": 3000} 
	},


	"consumeboxarray[]{}":{
		"prefix":"consumeboxarray",
		"body":[
			"\\consumeboxarray[${2:name}]{${1:index}}"
		],
		"luasnip": {"priority": 1000} 
	},


	"consumetcboxarray{}{}":{
		"prefix":"consumetcboxarray",
		"body":[
			"\\consumetcboxarray{${1:index}}{${2:options%keyvals}}"
		],
		"luasnip": {"priority": 3000} 
	},


	"consumetcboxarray[]{}{}":{
		"prefix":"consumetcboxarray",
		"body":[
			"\\consumetcboxarray[${3:name}]{${1:index}}{${2:options%keyvals}}"
		],
		"luasnip": {"priority": 1000} 
	},


	"boxarraygetbox{}{}":{
		"prefix":"boxarraygetbox",
		"body":[
			"\\boxarraygetbox{${1:macro%cmd}}{${2:index}}"
		],
		"luasnip": {"priority": 3000} 
	},


	"boxarraygetbox[]{}{}":{
		"prefix":"boxarraygetbox",
		"body":[
			"\\boxarraygetbox[${3:name}]{${1:macro%cmd}}{${2:index}}"
		],
		"luasnip": {"priority": 1000} 
	},


	"ifboxarrayempty{}{}{}":{
		"prefix":"ifboxarrayempty",
		"body":[
			"\\ifboxarrayempty{${1:index}}{${2:true}}{${3:false}}"
		],
		"luasnip": {"priority": 3000} 
	},


	"ifboxarrayempty[]{}{}{}":{
		"prefix":"ifboxarrayempty",
		"body":[
			"\\ifboxarrayempty[${4:name}]{${1:index}}{${2:true}}{${3:false}}"
		],
		"luasnip": {"priority": 1000} 
	},


	"boxarraygetwidth{}{}":{
		"prefix":"boxarraygetwidth",
		"body":[
			"\\boxarraygetwidth{${1:macro%cmd}}{${2:index}}"
		],
		"luasnip": {"priority": 3000} 
	},


	"boxarraygetwidth[]{}{}":{
		"prefix":"boxarraygetwidth",
		"body":[
			"\\boxarraygetwidth[${3:name}]{${1:macro%cmd}}{${2:index}}"
		],
		"luasnip": {"priority": 1000} 
	},


	"boxarraygetheight{}{}":{
		"prefix":"boxarraygetheight",
		"body":[
			"\\boxarraygetheight{${1:macro%cmd}}{${2:index}}"
		],
		"luasnip": {"priority": 3000} 
	},


	"boxarraygetheight[]{}{}":{
		"prefix":"boxarraygetheight",
		"body":[
			"\\boxarraygetheight[${3:name}]{${1:macro%cmd}}{${2:index}}"
		],
		"luasnip": {"priority": 1000} 
	},


	"boxarraygetdepth{}{}":{
		"prefix":"boxarraygetdepth",
		"body":[
			"\\boxarraygetdepth{${1:macro%cmd}}{${2:index}}"
		],
		"luasnip": {"priority": 3000} 
	},


	"boxarraygetdepth[]{}{}":{
		"prefix":"boxarraygetdepth",
		"body":[
			"\\boxarraygetdepth[${3:name}]{${1:macro%cmd}}{${2:index}}"
		],
		"luasnip": {"priority": 1000} 
	},


	"boxarraygettotalheight{}{}":{
		"prefix":"boxarraygettotalheight",
		"body":[
			"\\boxarraygettotalheight{${1:macro%cmd}}{${2:index}}"
		],
		"luasnip": {"priority": 3000} 
	},


	"boxarraygettotalheight[]{}{}":{
		"prefix":"boxarraygettotalheight",
		"body":[
			"\\boxarraygettotalheight[${3:name}]{${1:macro%cmd}}{${2:index}}"
		],
		"luasnip": {"priority": 1000} 
	},


	"boxarraystore{}":{
		"prefix":"boxarraystore",
		"body":[
			"\\begin{boxarraystore}",
				"\t{${1:name}}",
			"\\end{boxarraystore}"
		],
		"luasnip": {"priority": 3000} 
	}
}
