{


	"cat":{
		"prefix":"cat",
		"body":[
			"\\cat"
		]
	},


	"cathookbackground":{
		"prefix":"cathookbackground",
		"body":[
			"\\cathookbackground"
		]
	},


	"cathookbelly":{
		"prefix":"cathookbelly",
		"body":[
			"\\cathookbelly"
		]
	},


	"cathookbody":{
		"prefix":"cathookbody",
		"body":[
			"\\cathookbody"
		]
	},


	"cathookforeground":{
		"prefix":"cathookforeground",
		"body":[
			"\\cathookforeground"
		]
	},


	"tikzlinghookbackground":{
		"prefix":"tikzlinghookbackground",
		"body":[
			"\\tikzlinghookbackground"
		]
	},


	"tikzlinghookbelly":{
		"prefix":"tikzlinghookbelly",
		"body":[
			"\\tikzlinghookbelly"
		]
	},


	"tikzlinghookbody":{
		"prefix":"tikzlinghookbody",
		"body":[
			"\\tikzlinghookbody"
		]
	},


	"tikzlinghookforeground":{
		"prefix":"tikzlinghookforeground",
		"body":[
			"\\tikzlinghookforeground"
		]
	},


	"cat[]":{
		"prefix":"cat",
		"body":[
			"\\cat[${1:options%keyvals}]"
		]
	}
}
